{
  "users": [
    {
      "name": "Tomas",
      "email": "tbuixa@gmail.com",
      "password": "abcd1234",
      "transactions": [],
      "monthlyBudget": "5000",
      "monthlySpend": 0,
      "preferredCurrency": "",
      "id": 1
    },
    {
      "name": "Galo",
      "email": "galofazio@gmail.com",
      "password": "galote123",
      "transactions": [
        {
          "description": "Sueldo Noviembre",
          "date": "2023-10-31",
          "amount": 20000,
          "category": "noCategory",
          "sender": "Jefe"
        }
      ],
      "monthlyBudget": 40000,
      "monthlySpend": 0,
      "preferredCurrency": "",
      "id": 2
    },
    {
      "name": "Francisco",
      "email": "fr4nciscoescobar@gmail.com",
      "password": "panchote123",
      "transactions": [
        {
          "description": "dasdasd",
          "date": "2023-10-04",
          "amount": 10000,
          "category": "services",
          "comment": "123456",
          "sender": "Galote"
        }
      ],
      "monthlyBudget": 130000,
      "monthlySpend": 55000,
      "preferredCurrency": "",
      "id": 3
    },
    {
      "name": "Franco",
      "email": "francoferro@gmail.com",
      "password": "francote123",
      "transactions": [],
      "monthlyBudget": 0,
      "monthlySpend": 0,
      "preferredCurrency": "ARS",
      "id": 4
    },
    {
      "name": "adsasdas",
      "email": "sdadadasd",
      "password": "fadfafaf",
      "transactions": [],
      "monthlyBudget": 0,
      "monthlySpend": 0,
      "preferredCurrency": "ARS",
      "id": 5
    },
    {
      "name": "Lester",
      "email": "lesterCrest@gmail.com",
      "password": "lestote123",
      "transactions": [],
      "monthlyBudget": 0,
      "monthlySpend": 0,
      "preferredCurrency": "ARS",
      "id": 6
    }
  ]
}